sapia/__init__.py
sapia-0.0.1.dev0.dist-info/LICENSE
sapia-0.0.1.dev0.dist-info/METADATA
sapia-0.0.1.dev0.dist-info/WHEEL
sapia-0.0.1.dev0.dist-info/top_level.txt
sapia-0.0.1.dev0.dist-info/RECORD
